{"metadata":{"customers_affected":1996,"outage_count":19,"last_updated":"2024-07-14T02:14:14+00:00"},"featureCollection":{"type":"FeatureCollection","features":[{"type":"Feature","properties":{"id":"996687","point_of_interest":{"type":"Feature","properties":{},"geometry":{"type":"Point","coordinates":["-122.66830","47.56098"]}},"title":"Bremerton","start_time":{"id":"start_time","name":"Start time","value":"07/13 05:34 PM","no_display":false},"customers_impacted":{"id":"customers_impacted","name":"Customers impacted","value":"1","no_display":false},"status":{"id":"status","name":"Status","value":"Repair crew onsite","no_display":false},"cause":{"id":"cause","name":"Cause","value":"Under Investigation","no_display":false},"last_update":{"id":"last_update","name":"Last update","value":"07/13 07:10 PM","no_display":false},"est_restoration_time":{"id":"est_restoration_time","name":"Est. restoration time","value":"07/13 11:00 PM","no_display":false}},"geometry":{"type":"Polygon","coordinates":[[[-122.66817,47.55637],[-122.66808,47.55635],[-122.66425,47.55768],[-122.66421,47.55772],[-122.66461,47.56174],[-122.66461,47.56174],[-122.66476,47.56276],[-122.66477,47.56279],[-122.66743,47.56502],[-122.66745,47.56503],[-122.66959,47.56591],[-122.66969,47.56589],[-122.67337,47.56092],[-122.67336,47.56088],[-122.66817,47.55637]]]}},{"type":"Feature","properties":{"id":"996755","point_of_interest":{"type":"Feature","properties":{},"geometry":{"type":"Point","coordinates":["-122.07723","47.12117"]}},"title":"Buckley","start_time":{"id":"start_time","name":"Start time","value":"07/13 05:58 PM","no_display":false},"customers_impacted":{"id":"customers_impacted","name":"Customers impacted","value":"35","no_display":false},"status":{"id":"status","name":"Status","value":"Waiting for repairs","no_display":false},"cause":{"id":"cause","name":"Cause","value":"Under Investigation","no_display":false},"last_update":{"id":"last_update","name":"Last update","value":"07/13 07:10 PM","no_display":false},"est_restoration_time":{"id":"est_restoration_time","name":"Est. restoration time","value":"07/13 08:00 PM","no_display":false}},"geometry":{"type":"Polygon","coordinates":[[[-122.0815,47.11734],[-122.08147,47.11735],[-122.07141,47.11966],[-122.07136,47.1197],[-122.07046,47.12239],[-122.07046,47.1224],[-122.07038,47.12426],[-122.07041,47.1243],[-122.07374,47.12577],[-122.07381,47.12577],[-122.08361,47.12132],[-122.08363,47.1213],[-122.08519,47.11889],[-122.08519,47.11887],[-122.08528,47.11783],[-122.08523,47.11778],[-122.08372,47.11752],[-122.08371,47.11752],[-122.0815,47.11734]]]}},{"type":"Feature","properties":{"id":"996765","point_of_interest":{"type":"Feature","properties":{},"geometry":{"type":"Point","coordinates":["-122.33767","48.51289"]}},"title":"Burlington","start_time":{"id":"start_time","name":"Start time","value":"07/13 07:05 PM","no_display":false},"customers_impacted":{"id":"customers_impacted","name":"Customers impacted","value":"6","no_display":false},"status":{"id":"status","name":"Status","value":"Outage reported","no_display":false},"cause":{"id":"cause","name":"Cause","value":"Under Investigation","no_display":false},"last_update":{"id":"last_update","name":"Last update","value":"07/13 07:10 PM","no_display":false},"est_restoration_time":{"id":"est_restoration_time","name":"Est. restoration time","value":"07/13 09:30 PM","no_display":false}},"geometry":{"type":"Polygon","coordinates":[[[-122.33809,48.51225],[-122.33798,48.51221],[-122.33734,48.51261],[-122.33732,48.51265],[-122.33752,48.51377],[-122.33765,48.51377],[-122.33809,48.51225]]]}},{"type":"Feature","properties":{"id":"996764","point_of_interest":{"type":"Feature","properties":{},"geometry":{"type":"Point","coordinates":["-122.04145","47.07521"]}},"title":"Carbonado","start_time":{"id":"start_time","name":"Start time","value":"07/13 07:04 PM","no_display":false},"customers_impacted":{"id":"customers_impacted","name":"Customers impacted","value":"1773","no_display":false},"status":{"id":"status","name":"Status","value":"Outage reported","no_display":false},"cause":{"id":"cause","name":"Cause","value":"Under Investigation","no_display":false},"last_update":{"id":"last_update","name":"Last update","value":"07/13 07:10 PM","no_display":false},"est_restoration_time":{"id":"est_restoration_time","name":"Est. restoration time","value":"07/13 09:30 PM","no_display":false}},"geometry":{"type":"Polygon","coordinates":[[[-121.961,46.98723],[-121.96093,46.98725],[-121.95961,46.98853],[-121.9596,46.98856],[-122.01248,47.11017],[-122.01248,47.11018],[-122.01325,47.11128],[-122.01326,47.11129],[-122.04861,47.14044],[-122.04866,47.14046],[-122.0514,47.14043],[-122.0514,47.14043],[-122.0914,47.1384],[-122.09141,47.1384],[-122.09466,47.13784],[-122.09468,47.13783],[-122.11548,47.12714],[-122.1155,47.12712],[-122.12165,47.11625],[-122.12166,47.11624],[-122.12346,47.11002],[-122.12346,47.11001],[-122.12349,47.10817],[-122.12348,47.10815],[-122.0441,47.02901],[-122.04409,47.029],[-121.97846,46.99171],[-121.97845,46.99171],[-121.97244,46.98942],[-121.97243,46.98941],[-121.961,46.98723]]]}},{"type":"Feature","properties":{"id":"909029","point_of_interest":{"type":"Feature","properties":{},"geometry":{"type":"Point","coordinates":["-121.20300","47.26446"]}},"title":"Easton","start_time":{"id":"start_time","name":"Start time","value":"07/09 09:35 AM","no_display":false},"customers_impacted":{"id":"customers_impacted","name":"Customers impacted","value":"1","no_display":false},"status":{"id":"status","name":"Status","value":"Repair crew onsite","no_display":false},"cause":{"id":"cause","name":"Cause","value":"Scheduled Outage","no_display":false},"last_update":{"id":"last_update","name":"Last update","value":"07/13 07:10 PM","no_display":false}},"geometry":{"type":"Polygon","coordinates":[[[-121.20294,47.26446],[-121.20294,47.26447],[-121.20294,47.26448],[-121.20295,47.26449],[-121.20296,47.26449],[-121.20297,47.2645],[-121.20298,47.2645],[-121.20299,47.26451],[-121.20301,47.26451],[-121.20302,47.26451],[-121.20303,47.2645],[-121.20304,47.2645],[-121.20305,47.26449],[-121.20306,47.26449],[-121.20307,47.26448],[-121.20307,47.26447],[-121.20307,47.26446],[-121.20307,47.26445],[-121.20307,47.26444],[-121.20306,47.26444],[-121.20305,47.26443],[-121.20304,47.26442],[-121.20303,47.26442],[-121.20302,47.26442],[-121.20301,47.26442],[-121.20299,47.26442],[-121.20298,47.26442],[-121.20297,47.26442],[-121.20296,47.26443],[-121.20295,47.26444],[-121.20294,47.26445],[-121.20294,47.26445],[-121.20294,47.26446]]]}},{"type":"Feature","properties":{"id":"996753","point_of_interest":{"type":"Feature","properties":{},"geometry":{"type":"Point","coordinates":["-121.86373","47.56313"]}},"title":"Fall City","start_time":{"id":"start_time","name":"Start time","value":"07/13 05:41 PM","no_display":false},"customers_impacted":{"id":"customers_impacted","name":"Customers impacted","value":"8","no_display":false},"status":{"id":"status","name":"Status","value":"Waiting for repairs","no_display":false},"cause":{"id":"cause","name":"Cause","value":"Trees/Vegetation","no_display":false},"last_update":{"id":"last_update","name":"Last update","value":"07/13 07:10 PM","no_display":false},"est_restoration_time":{"id":"est_restoration_time","name":"Est. restoration time","value":"07/14 12:00 AM","no_display":false}},"geometry":{"type":"Polygon","coordinates":[[[-121.86366,47.56313],[-121.86367,47.56313],[-121.86367,47.56314],[-121.86368,47.56315],[-121.86368,47.56316],[-121.86369,47.56316],[-121.86371,47.56317],[-121.86372,47.56317],[-121.86373,47.56317],[-121.86374,47.56317],[-121.86376,47.56317],[-121.86377,47.56316],[-121.86378,47.56316],[-121.86379,47.56315],[-121.86379,47.56314],[-121.8638,47.56313],[-121.8638,47.56312],[-121.8638,47.56312],[-121.86379,47.56311],[-121.86379,47.5631],[-121.86378,47.56309],[-121.86377,47.56309],[-121.86375,47.56308],[-121.86374,47.56308],[-121.86373,47.56308],[-121.86372,47.56308],[-121.8637,47.56308],[-121.86369,47.56309],[-121.86368,47.56309],[-121.86367,47.5631],[-121.86367,47.56311],[-121.86366,47.56312],[-121.86366,47.56313]]]}},{"type":"Feature","properties":{"id":"989021","point_of_interest":{"type":"Feature","properties":{},"geometry":{"type":"Point","coordinates":["-122.59187","48.87040"]}},"title":"Ferndale","start_time":{"id":"start_time","name":"Start time","value":"07/12 09:04 AM","no_display":false},"customers_impacted":{"id":"customers_impacted","name":"Customers impacted","value":"1","no_display":false},"status":{"id":"status","name":"Status","value":"Repair crew onsite","no_display":false},"cause":{"id":"cause","name":"Cause","value":"Scheduled Outage","no_display":false},"last_update":{"id":"last_update","name":"Last update","value":"07/13 07:10 PM","no_display":false}},"geometry":{"type":"Polygon","coordinates":[[[-122.59179,48.8704],[-122.5918,48.87041],[-122.5918,48.87042],[-122.59181,48.87043],[-122.59182,48.87044],[-122.59183,48.87044],[-122.59184,48.87045],[-122.59185,48.87045],[-122.59186,48.87045],[-122.59188,48.87045],[-122.59189,48.87044],[-122.5919,48.87044],[-122.59191,48.87043],[-122.59192,48.87043],[-122.59193,48.87042],[-122.59193,48.87041],[-122.59193,48.8704],[-122.59193,48.87039],[-122.59193,48.87039],[-122.59192,48.87038],[-122.59191,48.87037],[-122.5919,48.87037],[-122.59189,48.87036],[-122.59187,48.87036],[-122.59186,48.87036],[-122.59185,48.87036],[-122.59184,48.87036],[-122.59182,48.87037],[-122.59181,48.87037],[-122.59181,48.87038],[-122.5918,48.87039],[-122.5918,48.8704],[-122.59179,48.8704]]]}},{"type":"Feature","properties":{"id":"996746","point_of_interest":{"type":"Feature","properties":{},"geometry":{"type":"Point","coordinates":["-122.52626","47.75927"]}},"title":"Indianola","start_time":{"id":"start_time","name":"Start time","value":"07/13 04:53 PM","no_display":false},"customers_impacted":{"id":"customers_impacted","name":"Customers impacted","value":"34","no_display":false},"status":{"id":"status","name":"Status","value":"Outage reported","no_display":false},"cause":{"id":"cause","name":"Cause","value":"Under Investigation","no_display":false},"last_update":{"id":"last_update","name":"Last update","value":"07/13 07:10 PM","no_display":false},"est_restoration_time":{"id":"est_restoration_time","name":"Est. restoration time","value":"07/13 08:00 PM","no_display":false}},"geometry":{"type":"Polygon","coordinates":[[[-122.52445,47.7553],[-122.52444,47.7553],[-122.52206,47.75543],[-122.52201,47.75545],[-122.52117,47.75643],[-122.52116,47.75645],[-122.521,47.75721],[-122.521,47.75722],[-122.52106,47.75794],[-122.52107,47.75796],[-122.52494,47.76161],[-122.52495,47.76162],[-122.53074,47.76502],[-122.53085,47.76499],[-122.5307,47.76152],[-122.5307,47.76151],[-122.52815,47.75646],[-122.52814,47.75645],[-122.52679,47.75537],[-122.52674,47.75535],[-122.52445,47.7553]]]}},{"type":"Feature","properties":{"id":"996763","point_of_interest":{"type":"Feature","properties":{},"geometry":{"type":"Point","coordinates":["-122.22208","47.38980"]}},"title":"Kent","start_time":{"id":"start_time","name":"Start time","value":"07/13 06:58 PM","no_display":false},"customers_impacted":{"id":"customers_impacted","name":"Customers impacted","value":"5","no_display":false},"status":{"id":"status","name":"Status","value":"Outage reported","no_display":false},"cause":{"id":"cause","name":"Cause","value":"Under Investigation","no_display":false},"last_update":{"id":"last_update","name":"Last update","value":"07/13 07:10 PM","no_display":false},"est_restoration_time":{"id":"est_restoration_time","name":"Est. restoration time","value":"07/13 09:00 PM","no_display":false}},"geometry":{"type":"Polygon","coordinates":[[[-122.22204,47.3895],[-122.22194,47.38952],[-122.22175,47.38993],[-122.22176,47.38996],[-122.2219,47.3901],[-122.22201,47.39011],[-122.22247,47.38976],[-122.22246,47.3897],[-122.22204,47.3895]]]}},{"type":"Feature","properties":{"id":"996255","point_of_interest":{"type":"Feature","properties":{},"geometry":{"type":"Point","coordinates":["-122.13368","47.64637"]}},"title":"Overlake","start_time":{"id":"start_time","name":"Start time","value":"07/13 07:43 AM","no_display":false},"customers_impacted":{"id":"customers_impacted","name":"Customers impacted","value":"1","no_display":false},"status":{"id":"status","name":"Status","value":"Repair crew onsite","no_display":false},"cause":{"id":"cause","name":"Cause","value":"Scheduled Outage","no_display":false},"last_update":{"id":"last_update","name":"Last update","value":"07/13 07:10 PM","no_display":false}},"geometry":{"type":"Polygon","coordinates":[[[-122.13362,47.64637],[-122.13362,47.64638],[-122.13362,47.64639],[-122.13363,47.6464],[-122.13364,47.6464],[-122.13365,47.64641],[-122.13366,47.64641],[-122.13367,47.64641],[-122.13368,47.64642],[-122.1337,47.64641],[-122.13371,47.64641],[-122.13372,47.64641],[-122.13373,47.6464],[-122.13374,47.64639],[-122.13375,47.64639],[-122.13375,47.64638],[-122.13375,47.64637],[-122.13375,47.64636],[-122.13374,47.64635],[-122.13374,47.64634],[-122.13373,47.64634],[-122.13372,47.64633],[-122.13371,47.64633],[-122.1337,47.64633],[-122.13368,47.64633],[-122.13367,47.64633],[-122.13366,47.64633],[-122.13365,47.64633],[-122.13364,47.64634],[-122.13363,47.64635],[-122.13362,47.64635],[-122.13362,47.64636],[-122.13362,47.64637]]]}},{"type":"Feature","properties":{"id":"996733","point_of_interest":{"type":"Feature","properties":{},"geometry":{"type":"Point","coordinates":["-122.67638","47.43209"]}},"title":"Port Orchard","start_time":{"id":"start_time","name":"Start time","value":"07/13 03:30 PM","no_display":false},"customers_impacted":{"id":"customers_impacted","name":"Customers impacted","value":"1","no_display":false},"status":{"id":"status","name":"Status","value":"Outage reported","no_display":false},"cause":{"id":"cause","name":"Cause","value":"Under Investigation","no_display":false},"last_update":{"id":"last_update","name":"Last update","value":"07/13 07:10 PM","no_display":false},"est_restoration_time":{"id":"est_restoration_time","name":"Est. restoration time","value":"07/13 08:30 PM","no_display":false}},"geometry":{"type":"Polygon","coordinates":[[[-122.67632,47.43209],[-122.67632,47.4321],[-122.67632,47.4321],[-122.67633,47.43211],[-122.67634,47.43212],[-122.67635,47.43212],[-122.67636,47.43213],[-122.67637,47.43213],[-122.67638,47.43213],[-122.6764,47.43213],[-122.67641,47.43213],[-122.67642,47.43212],[-122.67643,47.43212],[-122.67644,47.43211],[-122.67644,47.4321],[-122.67645,47.43209],[-122.67645,47.43208],[-122.67645,47.43208],[-122.67644,47.43207],[-122.67644,47.43206],[-122.67643,47.43205],[-122.67642,47.43205],[-122.67641,47.43204],[-122.67639,47.43204],[-122.67638,47.43204],[-122.67637,47.43204],[-122.67636,47.43204],[-122.67634,47.43205],[-122.67633,47.43205],[-122.67633,47.43206],[-122.67632,47.43207],[-122.67632,47.43208],[-122.67632,47.43209]]]}},{"type":"Feature","properties":{"id":"996705","point_of_interest":{"type":"Feature","properties":{},"geometry":{"type":"Point","coordinates":["-122.59717","47.72960"]}},"title":"Poulsbo","start_time":{"id":"start_time","name":"Start time","value":"07/13 01:34 PM","no_display":false},"customers_impacted":{"id":"customers_impacted","name":"Customers impacted","value":"3","no_display":false},"status":{"id":"status","name":"Status","value":"Crew assigned","no_display":false},"cause":{"id":"cause","name":"Cause","value":"Trees/Vegetation","no_display":false},"last_update":{"id":"last_update","name":"Last update","value":"07/13 07:10 PM","no_display":false},"est_restoration_time":{"id":"est_restoration_time","name":"Est. restoration time","value":"07/13 11:00 PM","no_display":false}},"geometry":{"type":"Polygon","coordinates":[[[-122.59777,47.72959],[-122.59657,47.72953],[-122.59656,47.72953],[-122.59655,47.72953],[-122.59653,47.72953],[-122.59652,47.72954],[-122.59652,47.72954],[-122.59651,47.72955],[-122.5965,47.72956],[-122.5965,47.72957],[-122.5965,47.72958],[-122.5965,47.72959],[-122.59651,47.72959],[-122.59652,47.7296],[-122.59653,47.72961],[-122.59654,47.72961],[-122.59655,47.72962],[-122.59656,47.72962],[-122.59776,47.72968],[-122.59778,47.72968],[-122.59779,47.72968],[-122.5978,47.72967],[-122.59781,47.72967],[-122.59782,47.72966],[-122.59783,47.72965],[-122.59783,47.72965],[-122.59784,47.72964],[-122.59784,47.72963],[-122.59783,47.72962],[-122.59783,47.72961],[-122.59782,47.7296],[-122.59781,47.7296],[-122.5978,47.72959],[-122.59779,47.72959],[-122.59777,47.72959]]]}},{"type":"Feature","properties":{"id":"996707","point_of_interest":{"type":"Feature","properties":{},"geometry":{"type":"Point","coordinates":["-122.66908","47.80739"]}},"title":"Poulsbo","start_time":{"id":"start_time","name":"Start time","value":"07/13 01:49 PM","no_display":false},"customers_impacted":{"id":"customers_impacted","name":"Customers impacted","value":"6","no_display":false},"status":{"id":"status","name":"Status","value":"Outage reported","no_display":false},"cause":{"id":"cause","name":"Cause","value":"Under Investigation","no_display":false},"last_update":{"id":"last_update","name":"Last update","value":"07/13 07:10 PM","no_display":false},"est_restoration_time":{"id":"est_restoration_time","name":"Est. restoration time","value":"07/13 08:00 PM","no_display":false}},"geometry":{"type":"Polygon","coordinates":[[[-122.66926,47.80696],[-122.66916,47.80696],[-122.6684,47.80747],[-122.66841,47.80754],[-122.66869,47.80768],[-122.66873,47.80769],[-122.66911,47.80769],[-122.66913,47.80769],[-122.66958,47.80761],[-122.66963,47.80756],[-122.66951,47.80719],[-122.6695,47.80717],[-122.66926,47.80696]]]}},{"type":"Feature","properties":{"id":"996752","point_of_interest":{"type":"Feature","properties":{},"geometry":{"type":"Point","coordinates":["-122.09718","47.70892"]}},"title":"Redmond","start_time":{"id":"start_time","name":"Start time","value":"07/13 05:40 PM","no_display":false},"customers_impacted":{"id":"customers_impacted","name":"Customers impacted","value":"5","no_display":false},"status":{"id":"status","name":"Status","value":"Outage reported","no_display":false},"cause":{"id":"cause","name":"Cause","value":"Under Investigation","no_display":false},"last_update":{"id":"last_update","name":"Last update","value":"07/13 07:10 PM","no_display":false},"est_restoration_time":{"id":"est_restoration_time","name":"Est. restoration time","value":"07/13 08:00 PM","no_display":false}},"geometry":{"type":"Polygon","coordinates":[[[-122.09669,47.70824],[-122.09662,47.70825],[-122.09596,47.70866],[-122.09594,47.70871],[-122.0964,47.70946],[-122.09646,47.70949],[-122.09795,47.70953],[-122.09802,47.7095],[-122.09849,47.70864],[-122.09845,47.70858],[-122.09669,47.70824]]]}},{"type":"Feature","properties":{"id":"996754","point_of_interest":{"type":"Feature","properties":{},"geometry":{"type":"Point","coordinates":["-122.56609","46.96011"]}},"title":"Roy","start_time":{"id":"start_time","name":"Start time","value":"07/13 05:49 PM","no_display":false},"customers_impacted":{"id":"customers_impacted","name":"Customers impacted","value":"6","no_display":false},"status":{"id":"status","name":"Status","value":"Waiting for repairs","no_display":false},"cause":{"id":"cause","name":"Cause","value":"Under Investigation","no_display":false},"last_update":{"id":"last_update","name":"Last update","value":"07/13 07:10 PM","no_display":false},"est_restoration_time":{"id":"est_restoration_time","name":"Est. restoration time","value":"07/13 08:00 PM","no_display":false}},"geometry":{"type":"Polygon","coordinates":[[[-122.56336,46.95866],[-122.56328,46.95872],[-122.56361,46.95938],[-122.56361,46.95939],[-122.56473,46.96071],[-122.56477,46.96073],[-122.5662,46.96105],[-122.56623,46.96105],[-122.56991,46.9607],[-122.56992,46.96062],[-122.56336,46.95866]]]}},{"type":"Feature","properties":{"id":"996107","point_of_interest":{"type":"Feature","properties":{},"geometry":{"type":"Point","coordinates":["-121.33769","47.69442"]}},"title":"Skykomish","start_time":{"id":"start_time","name":"Start time","value":"07/10 02:11 PM","no_display":false},"customers_impacted":{"id":"customers_impacted","name":"Customers impacted","value":"2","no_display":false},"status":{"id":"status","name":"Status","value":"Waiting for repairs","no_display":false},"cause":{"id":"cause","name":"Cause","value":"Under Investigation","no_display":false},"last_update":{"id":"last_update","name":"Last update","value":"07/13 07:10 PM","no_display":false},"est_restoration_time":{"id":"est_restoration_time","name":"Est. restoration time","value":"07/15 06:00 PM","no_display":false}},"geometry":{"type":"Polygon","coordinates":[[[-121.33763,47.69446],[-121.33776,47.69446],[-121.33777,47.69446],[-121.33778,47.69446],[-121.33779,47.69445],[-121.3378,47.69445],[-121.33781,47.69444],[-121.33782,47.69443],[-121.33782,47.69442],[-121.33782,47.69442],[-121.33782,47.69441],[-121.33781,47.6944],[-121.33781,47.69439],[-121.3378,47.69438],[-121.33779,47.69438],[-121.33778,47.69438],[-121.33776,47.69437],[-121.33775,47.69437],[-121.33763,47.69437],[-121.33761,47.69438],[-121.3376,47.69438],[-121.33759,47.69438],[-121.33758,47.69439],[-121.33757,47.6944],[-121.33757,47.6944],[-121.33756,47.69441],[-121.33756,47.69442],[-121.33756,47.69443],[-121.33757,47.69444],[-121.33757,47.69445],[-121.33758,47.69445],[-121.33759,47.69446],[-121.3376,47.69446],[-121.33762,47.69446],[-121.33763,47.69446]]]}},{"type":"Feature","properties":{"id":"996668","point_of_interest":{"type":"Feature","properties":{},"geometry":{"type":"Point","coordinates":["-122.21182","47.60349"]}},"title":"West Bellevue","start_time":{"id":"start_time","name":"Start time","value":"07/13 11:25 AM","no_display":false},"customers_impacted":{"id":"customers_impacted","name":"Customers impacted","value":"39","no_display":false},"status":{"id":"status","name":"Status","value":"Repair crew onsite","no_display":false},"cause":{"id":"cause","name":"Cause","value":"Equipment Failure","no_display":false},"last_update":{"id":"last_update","name":"Last update","value":"07/13 07:10 PM","no_display":false},"est_restoration_time":{"id":"est_restoration_time","name":"Est. restoration time","value":"07/13 08:30 PM","no_display":false}},"geometry":{"type":"Polygon","coordinates":[[[-122.21186,47.60169],[-122.21185,47.60169],[-122.21057,47.60177],[-122.21057,47.60177],[-122.21011,47.60181],[-122.21007,47.60183],[-122.20872,47.60342],[-122.20872,47.60346],[-122.20947,47.60506],[-122.20948,47.60507],[-122.20981,47.60543],[-122.20987,47.60545],[-122.21181,47.60536],[-122.21184,47.60535],[-122.2153,47.60391],[-122.21532,47.60385],[-122.21488,47.60298],[-122.21488,47.60297],[-122.21433,47.60213],[-122.2143,47.6021],[-122.21325,47.60179],[-122.21323,47.60178],[-122.21186,47.60169]]]}},{"type":"Feature","properties":{"id":"996700","point_of_interest":{"type":"Feature","properties":{},"geometry":{"type":"Point","coordinates":["-122.20499","47.60237"]}},"title":"West Bellevue","start_time":{"id":"start_time","name":"Start time","value":"07/13 01:20 PM","no_display":false},"customers_impacted":{"id":"customers_impacted","name":"Customers impacted","value":"1","no_display":false},"status":{"id":"status","name":"Status","value":"Waiting for repairs","no_display":false},"cause":{"id":"cause","name":"Cause","value":"Equipment Failure","no_display":false},"last_update":{"id":"last_update","name":"Last update","value":"07/13 07:10 PM","no_display":false},"est_restoration_time":{"id":"est_restoration_time","name":"Est. restoration time","value":"07/13 08:30 PM","no_display":false}},"geometry":{"type":"Polygon","coordinates":[[[-122.20493,47.60237],[-122.20493,47.60238],[-122.20493,47.60239],[-122.20494,47.60239],[-122.20495,47.6024],[-122.20496,47.60241],[-122.20497,47.60241],[-122.20498,47.60241],[-122.205,47.60241],[-122.20501,47.60241],[-122.20502,47.60241],[-122.20503,47.60241],[-122.20504,47.6024],[-122.20505,47.60239],[-122.20506,47.60239],[-122.20506,47.60238],[-122.20506,47.60237],[-122.20506,47.60236],[-122.20506,47.60235],[-122.20505,47.60234],[-122.20504,47.60234],[-122.20503,47.60233],[-122.20502,47.60233],[-122.20501,47.60232],[-122.20499,47.60232],[-122.20498,47.60233],[-122.20497,47.60233],[-122.20496,47.60233],[-122.20495,47.60234],[-122.20494,47.60234],[-122.20493,47.60235],[-122.20493,47.60236],[-122.20493,47.60237]]]}},{"type":"Feature","properties":{"id":"996704","point_of_interest":{"type":"Feature","properties":{},"geometry":{"type":"Point","coordinates":["-122.20993","47.60297"]}},"title":"West Bellevue","start_time":{"id":"start_time","name":"Start time","value":"07/13 01:20 PM","no_display":false},"customers_impacted":{"id":"customers_impacted","name":"Customers impacted","value":"68","no_display":false},"status":{"id":"status","name":"Status","value":"Repair crew onsite","no_display":false},"cause":{"id":"cause","name":"Cause","value":"Equipment Failure","no_display":false},"last_update":{"id":"last_update","name":"Last update","value":"07/13 07:10 PM","no_display":false},"est_restoration_time":{"id":"est_restoration_time","name":"Est. restoration time","value":"07/13 08:30 PM","no_display":false}},"geometry":{"type":"Polygon","coordinates":[[[-122.20798,47.59989],[-122.20791,47.5999],[-122.2043,47.60229],[-122.20429,47.60234],[-122.20485,47.60305],[-122.20487,47.60306],[-122.20635,47.6038],[-122.20636,47.6038],[-122.21095,47.60571],[-122.21096,47.60571],[-122.21281,47.60628],[-122.21288,47.60627],[-122.21332,47.60597],[-122.21333,47.60596],[-122.21475,47.60353],[-122.21474,47.6035],[-122.21337,47.60168],[-122.21336,47.60167],[-122.21312,47.6015],[-122.2131,47.60149],[-122.20798,47.59989]]]}}]}}